{
  "author_chars": 0,
  "chunk_binding_sha256": "b1bd47c1653c2c5d189a2b21cc196bb4a84d1d89569fd7497772ece8a361e91c",
  "context_after_unit": "U-e9cc53e25f90",
  "context_before_unit": "U-ebbdf16ff740",
  "diff_path": "",
  "end": 36305,
  "end_line": 882,
  "file_id": "F00001",
  "hash_after": "",
  "hash_before": "e104671a96137dfd58498cef54fc963906f78e78a0382092332546f2c5bcf902",
  "heading_path": "GPT/Codex 中文风格深度语料报告 / 9. 真实脱敏原文证据 / 证据 114",
  "intensity": "STRUCTURAL",
  "line_count": 6,
  "masked_text": "[[PROTECTED:F00001-P00380:0973475275b2]]\n[[PROTECTED:F00001-P00381:062f993be5f6]]\r\n[[PROTECTED:F00001-P00382:23b91720699b]]\n\r\n",
  "mode": "REWRITE",
  "notes": "",
  "owner_chunk": "U-306d261d6a82",
  "part": 1,
  "protected_hashes_ok": "NOT_RUN",
  "protected_ids": [
    "F00001-P00380",
    "F00001-P00381",
    "F00001-P00382"
  ],
  "protected_spans": 3,
  "read_only_context_after": "[[PROTECTED:F00001-P00383:230621ad4c8b]]\n[[PROTECTED:F00001-P00384:f9f74bbd194a]]\r\n[[PROTECTED:F00001-P00385:926d211de3fa]]",
  "read_only_context_before": "[[PROTECTED:F00001-P00377:57baf89b615a]]\n[[PROTECTED:F00001-P00378:710d17977395]]\r\n[[PROTECTED:F00001-P00379:e0e4aed6e531]]",
  "scene": "GENERAL",
  "scene_document_prior": "",
  "scene_requested": "GENERAL",
  "scene_routing_ambiguous_scenes": [],
  "scene_routing_decision": "EXPLICIT",
  "scene_routing_evidence": [],
  "scene_routing_margin": 0,
  "scene_routing_policy_revision": 2,
  "scene_routing_policy_sha256": "8d0f916d91b5753fd94d358c4b32e9a6c02b1f30120f43b4cbb2165dc1684450",
  "scene_routing_scores": {
    "COURSE": 0,
    "MODELING": 0,
    "RESEARCH": 0
  },
  "scene_routing_top_score": 0,
  "start": 36071,
  "start_line": 877,
  "status": "SKIPPED_PROTECTED",
  "structural_cross_unit_moves_allowed": false,
  "structural_inventory_sha256": "c9a42ed23b46e7d4e7d1c9576c77b0511abc937a7d07b273d11327bf8f64e3b3",
  "structural_paragraphs": [
    {
      "author_chars": 0,
      "lock_reason": "insufficient_author_prose",
      "movable": false,
      "ordinal": 1,
      "paragraph_id": "P001-950c3986d967",
      "protected_ids": [
        "F00001-P00380",
        "F00001-P00381",
        "F00001-P00382"
      ],
      "responsibility": "EXPOSITION",
      "sha256": "950c3986d9674ee38faafbd12aa77a499b2c17485438a96ce2fa01a6c1e215fe"
    }
  ],
  "structural_plan_schema": "humanize-structural-plan/v1",
  "structural_plan_status": "NOT_RUN",
  "structural_scope": "UNIT",
  "structural_title_lock": true,
  "style_validation": "NOT_RUN",
  "unit_id": "U-306d261d6a82",
  "voice_default_disclosure": true,
  "voice_profile_binding_scene": "GENERAL",
  "voice_profile_confidence": "DEFAULT",
  "voice_profile_id": "scene-default-general",
  "voice_profile_kind": "DEFAULT",
  "voice_profile_revision": 1,
  "voice_profile_sha256": "3b4eeeaeb3af397378ead360550371ff4632cbce6fceca8923479c53de23a112",
  "voice_profile_source": "SCENE_DEFAULT"
}
