{
  "author_chars": 0,
  "chunk_binding_sha256": "b1b5623584253e9504d346258dc702cca2bdbd63cf3d80152dbe01a32f6f8609",
  "context_after_unit": "U-b0c5851ccea3",
  "context_before_unit": "U-c26c1250d536",
  "diff_path": "",
  "end": 8593,
  "end_line": 234,
  "file_id": "F00001",
  "hash_after": "",
  "hash_before": "9fff0205988f81af2c59794183b3c41003a19f30c6a02759f3ccaef7571bf9a0",
  "heading_path": "GPT/Codex 中文风格深度语料报告 / 9. 真实脱敏原文证据 / 证据 6",
  "intensity": "STRUCTURAL",
  "line_count": 6,
  "masked_text": "[[PROTECTED:F00001-P00056:023f9b0326df]]\n[[PROTECTED:F00001-P00057:c68f416ca96a]]\r\n[[PROTECTED:F00001-P00058:1d846e396a8e]]\n\r\n",
  "mode": "REWRITE",
  "notes": "",
  "owner_chunk": "U-7c3d32f9a071",
  "part": 1,
  "protected_hashes_ok": "NOT_RUN",
  "protected_ids": [
    "F00001-P00056",
    "F00001-P00057",
    "F00001-P00058"
  ],
  "protected_spans": 3,
  "read_only_context_after": "[[PROTECTED:F00001-P00059:44492523a9d0]]\n[[PROTECTED:F00001-P00060:9d57f0ec5e6b]]\r\n[[PROTECTED:F00001-P00061:cea7f6fb1984]]",
  "read_only_context_before": "[[PROTECTED:F00001-P00053:1d8b45d54344]]\n[[PROTECTED:F00001-P00054:13bd5a517c39]]\r\n[[PROTECTED:F00001-P00055:47ac8aaf111f]]",
  "scene": "GENERAL",
  "scene_document_prior": "",
  "scene_requested": "GENERAL",
  "scene_routing_ambiguous_scenes": [],
  "scene_routing_decision": "EXPLICIT",
  "scene_routing_evidence": [],
  "scene_routing_margin": 0,
  "scene_routing_policy_revision": 2,
  "scene_routing_policy_sha256": "8d0f916d91b5753fd94d358c4b32e9a6c02b1f30120f43b4cbb2165dc1684450",
  "scene_routing_scores": {
    "COURSE": 0,
    "MODELING": 0,
    "RESEARCH": 0
  },
  "scene_routing_top_score": 0,
  "start": 8399,
  "start_line": 229,
  "status": "SKIPPED_PROTECTED",
  "structural_cross_unit_moves_allowed": false,
  "structural_inventory_sha256": "ddbf54a4fa0ce73a86f2d61631d5925a9c60d86572d2eb60f75a53fdaa798570",
  "structural_paragraphs": [
    {
      "author_chars": 0,
      "lock_reason": "insufficient_author_prose",
      "movable": false,
      "ordinal": 1,
      "paragraph_id": "P001-821d1925e13c",
      "protected_ids": [
        "F00001-P00056",
        "F00001-P00057",
        "F00001-P00058"
      ],
      "responsibility": "EXPOSITION",
      "sha256": "821d1925e13cff0f29d13107dec89014146a98a1a295beadcc952b605f5ed65d"
    }
  ],
  "structural_plan_schema": "humanize-structural-plan/v1",
  "structural_plan_status": "NOT_RUN",
  "structural_scope": "UNIT",
  "structural_title_lock": true,
  "style_validation": "NOT_RUN",
  "unit_id": "U-7c3d32f9a071",
  "voice_default_disclosure": true,
  "voice_profile_binding_scene": "GENERAL",
  "voice_profile_confidence": "DEFAULT",
  "voice_profile_id": "scene-default-general",
  "voice_profile_kind": "DEFAULT",
  "voice_profile_revision": 1,
  "voice_profile_sha256": "3b4eeeaeb3af397378ead360550371ff4632cbce6fceca8923479c53de23a112",
  "voice_profile_source": "SCENE_DEFAULT"
}
