{
  "author_chars": 0,
  "context_after_unit": "U-f1e62a593777",
  "context_before_unit": "U-fb217707a491",
  "diff_path": "",
  "end": 12117,
  "end_line": 212,
  "file_id": "F00001",
  "hash_after": "",
  "hash_before": "6553cddc35af650a90095cde44dbd808a011c3f07d63c753ea586bfac237d1c6",
  "heading_path": "问题二的模型建立与求解",
  "intensity": "BALANCED",
  "line_count": 2,
  "masked_text": "[[PROTECTED:F00001-P00329:ae55c763e4d7]]\n",
  "mode": "REWRITE",
  "notes": "",
  "owner_chunk": "U-d991425f019f",
  "part": 1,
  "protected_hashes_ok": "NOT_RUN",
  "protected_ids": [
    "F00001-P00329"
  ],
  "protected_spans": 1,
  "read_only_context_after": "[[PROTECTED:F00001-P00330:7d00b3dbb993]]\n问题二不单独做外推拟合，而是把问题一得到的 [[PROTECTED:F00001-P00331:7a702f97ebc7]] 作为上游食源代理，传入珍稀物种模块。这里 [[PROTECTED:F00001-P00332:297422400257]] 表示中层猎物资源，[[PROTECTED:F00001-P00333:3a16fddd1da7]] 和 [[PROTECTED:F00001-P00334:fdf30f5db1f3]] 分别表示江豚和长江鲟，[[PROTECTED:F00001-P00335:da8c27c394be]] 表示入侵竞争物种。为避免把自然恢复、通道修复和人工放流混在一起，先把题面事实与模型口径对应如表 [[PROTECTED:F00001-P00336:44d3d6345cfa]] 所示。\n[[PROTECTED:F00001-P00337:ff2eb9e78880]]{table}[htbp]\n[[PROTECTED:F00001-P00338:444090bde130]]\n[[PROTECTED:F00001-P00339:a95360f059e6]]{问题二的观测锚点与模型映射}\n[[PROTECTED:F00001-P00340:77e1e0701c7b]]\n[[PROTECTED:F00001-P00341:ff2eb9e78880]]{tabularx}{0.95[[PROTECTED:F00001-P00342:db686cb84689]]}{>{[[PROTECTED:F00001-P00343:e13c04e5f7fa]][[PROTECTED:F00001-P00344:4afb314fdcd4]]}p{2.4cm} >{[[PROTECTED:F00001-P00345:e13c04e5f7fa]][[PROTECTED:F00001-P00346:4afb314fdcd4]]}p{4.2cm} >{[[PROTECTED:F00001-P00347:e13c04e5f7fa]][[PROTECTED:F00001-P00348:4afb314fdcd4]]}p{3.6cm} X}\n[[PROTECTED:F00001-P00349:3000c3bd47e8]]\n事实来源 & 观测口径 & 对应模型量 & 角色 [[PROTECTED:F00001-P00350:b11b4ca186c0]]\n[[PROTECTED:F00001-P00351:3f9db2ae5742]]\n附件 1 & 洄游路径、大坝阻隔、鱼道连通性 & [[PROTECTED:F00001-P00352:0a95e0c00346]] & 硬事实锚点 [[PROT",
  "read_only_context_before": "[[PROTECTED:F00001-P00323:ff2eb9e78880]]{figure}[htbp]\n[[PROTECTED:F00001-P00324:444090bde130]]\n[[PROTECTED:F00001-P00325:39e863913a9e]]\n[[PROTECTED:F00001-P00326:a95360f059e6]]{问题一：校准后的禁渔与对照情景及观测锚点}\n[[PROTECTED:F00001-P00327:c1a928c1c2e2]]\n[[PROTECTED:F00001-P00328:06b3847e1b6f]]{figure}",
  "scene": "RESEARCH",
  "start": 12094,
  "start_line": 211,
  "status": "SKIPPED_PROTECTED",
  "style_validation": "NOT_RUN",
  "unit_id": "U-d991425f019f",
  "voice_default_disclosure": true,
  "voice_profile_binding_scene": "RESEARCH",
  "voice_profile_confidence": "DEFAULT",
  "voice_profile_id": "scene-default-research",
  "voice_profile_kind": "DEFAULT",
  "voice_profile_revision": 1,
  "voice_profile_sha256": "27bc2f98075de1183522db6025dd20899d4fd0a2ab2383887b987a691c08fe78",
  "voice_profile_source": "SCENE_DEFAULT"
}
