{
  "page": 57,
  "image": "tmp\\pdfs\\daofa_ocr\\pages\\page-57.png",
  "elapsed": [
    0.38318872451782227,
    0.03876376152038574,
    2.5991337299346924
  ],
  "entries": [
    {
      "text": "6.3国家行政机关",
      "score": 0.8224912464618683,
      "bbox": [
        629.0,
        129.0,
        937.0,
        172.0
      ]
    },
    {
      "text": "1.行政机关（国家权力机关的执行机关）：",
      "score": 0.9335205583345323,
      "bbox": [
        142.0,
        182.0,
        750.0,
        222.0
      ]
    },
    {
      "text": "①含义：行政机关是依据宪法设立的，依法行使国家行政职权，组织和管理国家行政事务",
      "score": 0.9300893038511276,
      "bbox": [
        141.0,
        224.0,
        1449.0,
        270.0
      ]
    },
    {
      "text": "的国家机关。",
      "score": 0.804513795035226,
      "bbox": [
        139.0,
        273.0,
        313.0,
        318.0
      ]
    },
    {
      "text": "②组成：我国行政机关由国务院及其领导的地方各级人民政府组成。",
      "score": 0.9178422227982552,
      "bbox": [
        139.0,
        320.0,
        1125.0,
        364.0
      ]
    },
    {
      "text": "③县级以上人民政府设置若干部门，这些部门分工不同，分别在各自职权范围内为人民群",
      "score": 0.932531763613224,
      "bbox": [
        144.0,
        368.0,
        1450.0,
        411.0
      ]
    },
    {
      "text": "众提供服务，他们相互配合，共同致力于提高为经济发展服务、为人民服务的能力和水平。",
      "score": 0.9409296556216914,
      "bbox": [
        137.0,
        413.0,
        1445.0,
        461.0
      ]
    },
    {
      "text": "2. 职权",
      "score": 0.7173508505026499,
      "bbox": [
        132.0,
        460.0,
        233.0,
        509.0
      ]
    },
    {
      "text": "(1) 内容",
      "score": 0.7182290383747646,
      "bbox": [
        143.0,
        511.0,
        283.0,
        552.0
      ]
    },
    {
      "text": "①根据宪法，我国县级以上人民政府主要管理经济、教育、科学、文化、卫生、体育事业、",
      "score": 0.9260860085487366,
      "bbox": [
        138.0,
        558.0,
        1446.0,
        599.0
      ]
    },
    {
      "text": "城乡建设事业和财政、民政、公安、民族事务、司法行政、计划生育等行政工作。",
      "score": 0.9400836358199248,
      "bbox": [
        136.0,
        606.0,
        1320.0,
        647.0
      ]
    },
    {
      "text": "②行政机关层级不同，职权也不同。国务院，即中央人民政府，是我国最高行政机关，统",
      "score": 0.9419458597898483,
      "bbox": [
        137.0,
        656.0,
        1450.0,
        697.0
      ]
    },
    {
      "text": "一领导地方各级人民政。",
      "score": 0.8615349332491556,
      "bbox": [
        136.0,
        708.0,
        521.0,
        750.0
      ]
    },
    {
      "text": "例：中央人民政府一广东省人民政府一一深圳市人民政府",
      "score": 0.9104834726223578,
      "bbox": [
        136.0,
        760.0,
        1002.0,
        802.0
      ]
    },
    {
      "text": "（2）要求（衍政机关如何依法行政)",
      "score": 0.8544333047337003,
      "bbox": [
        141.0,
        805.0,
        673.0,
        850.0
      ]
    },
    {
      "text": "①（从丛行政机关身来说）行政机关必须依法行政。行政机关享有哪些职权，具体如何行",
      "score": 0.9219660580158233,
      "bbox": [
        136.0,
        851.0,
        1449.0,
        892.0
      ]
    },
    {
      "text": "使职权，都必须严格遵照宪法和法律。行政机关要坚持法定职责必须为，法无授权不可为，",
      "score": 0.9291559763071013,
      "bbox": [
        134.0,
        895.0,
        1452.0,
        940.0
      ]
    },
    {
      "text": "勇于负责、敢于担当，坚决纠正不作为、乱作为，坚决克服懒政、怠政。",
      "score": 0.9272656187866674,
      "bbox": [
        135.0,
        946.0,
        1181.0,
        985.0
      ]
    },
    {
      "text": "②（从外部监督来说）行政机关的职权通常由行政机关工作人员具体实施。为了防止工作",
      "score": 0.8988575860857964,
      "bbox": [
        135.0,
        987.0,
        1451.0,
        1031.0
      ]
    },
    {
      "text": "制约，切实做到有权必有责，用权受监督，权责要对等，失责要追究，侵权要赔偿。",
      "score": 0.9115350826790458,
      "bbox": [
        134.0,
        1081.0,
        1366.0,
        1123.0
      ]
    },
    {
      "text": "3.行政机关与权力机关的关系？",
      "score": 0.8983908481895924,
      "bbox": [
        133.0,
        1188.0,
        588.0,
        1221.0
      ]
    },
    {
      "text": "①国家行政机关是国家权力机关的执行机关，负责贯彻执行国家权力机关通过的有关法律、",
      "score": 0.9366382345920656,
      "bbox": [
        136.0,
        1237.0,
        1442.0,
        1270.0
      ]
    },
    {
      "text": "决议和决定。",
      "score": 0.8546680808067322,
      "bbox": [
        134.0,
        1286.0,
        322.0,
        1325.0
      ]
    },
    {
      "text": "②各级人民政府对本级人民代表大会负责并报告工作。",
      "score": 0.9183450746536255,
      "bbox": [
        135.0,
        1337.0,
        915.0,
        1373.0
      ]
    },
    {
      "text": "③县级以上地方各级人民政府在本级人民代表大会闭会期间，对本级人大常委会负责并报",
      "score": 0.9126326367259026,
      "bbox": [
        134.0,
        1387.0,
        1445.0,
        1422.0
      ]
    },
    {
      "text": "告工作。",
      "score": 0.7992655515670777,
      "bbox": [
        133.0,
        1439.0,
        252.0,
        1474.0
      ]
    },
    {
      "text": "4.建设什么样的政府？",
      "score": 0.84571573138237,
      "bbox": [
        132.0,
        1541.0,
        455.0,
        1574.0
      ]
    },
    {
      "text": "①建设服务型政府。衍政机关必须全心全意为人民服务，努力建设人民满意的服务型政府。",
      "score": 0.9247269426904073,
      "bbox": [
        133.0,
        1585.0,
        1444.0,
        1626.0
      ]
    },
    {
      "text": "②建设依法行政的政府。行政机关享有哪些职权，具体如何行使职权，都必须严格遵照宪",
      "score": 0.910244844853878,
      "bbox": [
        137.0,
        1632.0,
        1447.0,
        1671.0
      ]
    },
    {
      "text": "法和法律。行政机关要坚持法定职责必须为，法无授权不可为，勇于负责、敢于担当，坚",
      "score": 0.9301801100373268,
      "bbox": [
        131.0,
        1678.0,
        1447.0,
        1716.0
      ]
    },
    {
      "text": "决纠正不作为、乱作为，坚决克服懒赖政、怠政。",
      "score": 0.8809082689492599,
      "bbox": [
        135.0,
        1727.0,
        833.0,
        1760.0
      ]
    },
    {
      "text": "③建设敢于当的政府。",
      "score": 0.8899841579523954,
      "bbox": [
        136.0,
        1771.0,
        516.0,
        1806.0
      ]
    },
    {
      "text": "④建设清正廉洁的政府",
      "score": 0.7691933079199358,
      "bbox": [
        134.0,
        1817.0,
        470.0,
        1854.0
      ]
    },
    {
      "text": "③建设阳光型政庭，做到政务公开，自觉接受人民监督。",
      "score": 0.8646772458003118,
      "bbox": [
        133.0,
        1860.0,
        974.0,
        1899.0
      ]
    },
    {
      "text": "（为什么要建设这样的政府？因为人民是国家的主人，行政机关的权力来自人民，是人民",
      "score": 0.9320880457758903,
      "bbox": [
        148.0,
        1910.0,
        1447.0,
        1949.0
      ]
    },
    {
      "text": "授予的。）",
      "score": 0.7359419067700704,
      "bbox": [
        133.0,
        1962.0,
        293.0,
        2002.0
      ]
    },
    {
      "text": "页5",
      "score": 0.6635201573371887,
      "bbox": [
        141.0,
        2045.0,
        202.0,
        2079.0
      ]
    },
    {
      "text": "57",
      "score": 0.6611524621645609,
      "bbox": [
        785.0,
        2070.0,
        874.0,
        2148.0
      ]
    },
    {
      "text": "扫描全能王 创建",
      "score": 0.8457870086034139,
      "bbox": [
        1328.0,
        2256.0,
        1597.0,
        2289.0
      ]
    }
  ],
  "lines": [
    {
      "text": "6.3国家行政机关",
      "score": 0.8224912464618683,
      "avg_score": 0.8224912464618683,
      "bbox": [
        629.0,
        129.0,
        937.0,
        172.0
      ]
    },
    {
      "text": "1.行政机关（国家权力机关的执行机关）：",
      "score": 0.9335205583345323,
      "avg_score": 0.9335205583345323,
      "bbox": [
        142.0,
        182.0,
        750.0,
        222.0
      ]
    },
    {
      "text": "①含义：行政机关是依据宪法设立的，依法行使国家行政职权，组织和管理国家行政事务",
      "score": 0.9300893038511276,
      "avg_score": 0.9300893038511276,
      "bbox": [
        141.0,
        224.0,
        1449.0,
        270.0
      ]
    },
    {
      "text": "的国家机关。",
      "score": 0.804513795035226,
      "avg_score": 0.804513795035226,
      "bbox": [
        139.0,
        273.0,
        313.0,
        318.0
      ]
    },
    {
      "text": "②组成：我国行政机关由国务院及其领导的地方各级人民政府组成。",
      "score": 0.9178422227982552,
      "avg_score": 0.9178422227982552,
      "bbox": [
        139.0,
        320.0,
        1125.0,
        364.0
      ]
    },
    {
      "text": "③县级以上人民政府设置若干部门，这些部门分工不同，分别在各自职权范围内为人民群",
      "score": 0.932531763613224,
      "avg_score": 0.932531763613224,
      "bbox": [
        144.0,
        368.0,
        1450.0,
        411.0
      ]
    },
    {
      "text": "众提供服务，他们相互配合，共同致力于提高为经济发展服务、为人民服务的能力和水平。",
      "score": 0.9409296556216914,
      "avg_score": 0.9409296556216914,
      "bbox": [
        137.0,
        413.0,
        1445.0,
        461.0
      ]
    },
    {
      "text": "2. 职权",
      "score": 0.7173508505026499,
      "avg_score": 0.7173508505026499,
      "bbox": [
        132.0,
        460.0,
        233.0,
        509.0
      ]
    },
    {
      "text": "(1) 内容",
      "score": 0.7182290383747646,
      "avg_score": 0.7182290383747646,
      "bbox": [
        143.0,
        511.0,
        283.0,
        552.0
      ]
    },
    {
      "text": "①根据宪法，我国县级以上人民政府主要管理经济、教育、科学、文化、卫生、体育事业、",
      "score": 0.9260860085487366,
      "avg_score": 0.9260860085487366,
      "bbox": [
        138.0,
        558.0,
        1446.0,
        599.0
      ]
    },
    {
      "text": "城乡建设事业和财政、民政、公安、民族事务、司法行政、计划生育等行政工作。",
      "score": 0.9400836358199248,
      "avg_score": 0.9400836358199248,
      "bbox": [
        136.0,
        606.0,
        1320.0,
        647.0
      ]
    },
    {
      "text": "②行政机关层级不同，职权也不同。国务院，即中央人民政府，是我国最高行政机关，统",
      "score": 0.9419458597898483,
      "avg_score": 0.9419458597898483,
      "bbox": [
        137.0,
        656.0,
        1450.0,
        697.0
      ]
    },
    {
      "text": "一领导地方各级人民政。",
      "score": 0.8615349332491556,
      "avg_score": 0.8615349332491556,
      "bbox": [
        136.0,
        708.0,
        521.0,
        750.0
      ]
    },
    {
      "text": "例：中央人民政府一广东省人民政府一一深圳市人民政府",
      "score": 0.9104834726223578,
      "avg_score": 0.9104834726223578,
      "bbox": [
        136.0,
        760.0,
        1002.0,
        802.0
      ]
    },
    {
      "text": "（2）要求（衍政机关如何依法行政)",
      "score": 0.8544333047337003,
      "avg_score": 0.8544333047337003,
      "bbox": [
        141.0,
        805.0,
        673.0,
        850.0
      ]
    },
    {
      "text": "①（从丛行政机关身来说）行政机关必须依法行政。行政机关享有哪些职权，具体如何行",
      "score": 0.9219660580158233,
      "avg_score": 0.9219660580158233,
      "bbox": [
        136.0,
        851.0,
        1449.0,
        892.0
      ]
    },
    {
      "text": "使职权，都必须严格遵照宪法和法律。行政机关要坚持法定职责必须为，法无授权不可为，",
      "score": 0.9291559763071013,
      "avg_score": 0.9291559763071013,
      "bbox": [
        134.0,
        895.0,
        1452.0,
        940.0
      ]
    },
    {
      "text": "勇于负责、敢于担当，坚决纠正不作为、乱作为，坚决克服懒政、怠政。",
      "score": 0.9272656187866674,
      "avg_score": 0.9272656187866674,
      "bbox": [
        135.0,
        946.0,
        1181.0,
        985.0
      ]
    },
    {
      "text": "②（从外部监督来说）行政机关的职权通常由行政机关工作人员具体实施。为了防止工作",
      "score": 0.8988575860857964,
      "avg_score": 0.8988575860857964,
      "bbox": [
        135.0,
        987.0,
        1451.0,
        1031.0
      ]
    },
    {
      "text": "制约，切实做到有权必有责，用权受监督，权责要对等，失责要追究，侵权要赔偿。",
      "score": 0.9115350826790458,
      "avg_score": 0.9115350826790458,
      "bbox": [
        134.0,
        1081.0,
        1366.0,
        1123.0
      ]
    },
    {
      "text": "3.行政机关与权力机关的关系？",
      "score": 0.8983908481895924,
      "avg_score": 0.8983908481895924,
      "bbox": [
        133.0,
        1188.0,
        588.0,
        1221.0
      ]
    },
    {
      "text": "①国家行政机关是国家权力机关的执行机关，负责贯彻执行国家权力机关通过的有关法律、",
      "score": 0.9366382345920656,
      "avg_score": 0.9366382345920656,
      "bbox": [
        136.0,
        1237.0,
        1442.0,
        1270.0
      ]
    },
    {
      "text": "决议和决定。",
      "score": 0.8546680808067322,
      "avg_score": 0.8546680808067322,
      "bbox": [
        134.0,
        1286.0,
        322.0,
        1325.0
      ]
    },
    {
      "text": "②各级人民政府对本级人民代表大会负责并报告工作。",
      "score": 0.9183450746536255,
      "avg_score": 0.9183450746536255,
      "bbox": [
        135.0,
        1337.0,
        915.0,
        1373.0
      ]
    },
    {
      "text": "③县级以上地方各级人民政府在本级人民代表大会闭会期间，对本级人大常委会负责并报",
      "score": 0.9126326367259026,
      "avg_score": 0.9126326367259026,
      "bbox": [
        134.0,
        1387.0,
        1445.0,
        1422.0
      ]
    },
    {
      "text": "告工作。",
      "score": 0.7992655515670777,
      "avg_score": 0.7992655515670777,
      "bbox": [
        133.0,
        1439.0,
        252.0,
        1474.0
      ]
    },
    {
      "text": "4.建设什么样的政府？",
      "score": 0.84571573138237,
      "avg_score": 0.84571573138237,
      "bbox": [
        132.0,
        1541.0,
        455.0,
        1574.0
      ]
    },
    {
      "text": "①建设服务型政府。衍政机关必须全心全意为人民服务，努力建设人民满意的服务型政府。",
      "score": 0.9247269426904073,
      "avg_score": 0.9247269426904073,
      "bbox": [
        133.0,
        1585.0,
        1444.0,
        1626.0
      ]
    },
    {
      "text": "②建设依法行政的政府。行政机关享有哪些职权，具体如何行使职权，都必须严格遵照宪",
      "score": 0.910244844853878,
      "avg_score": 0.910244844853878,
      "bbox": [
        137.0,
        1632.0,
        1447.0,
        1671.0
      ]
    },
    {
      "text": "法和法律。行政机关要坚持法定职责必须为，法无授权不可为，勇于负责、敢于担当，坚",
      "score": 0.9301801100373268,
      "avg_score": 0.9301801100373268,
      "bbox": [
        131.0,
        1678.0,
        1447.0,
        1716.0
      ]
    },
    {
      "text": "决纠正不作为、乱作为，坚决克服懒赖政、怠政。",
      "score": 0.8809082689492599,
      "avg_score": 0.8809082689492599,
      "bbox": [
        135.0,
        1727.0,
        833.0,
        1760.0
      ]
    },
    {
      "text": "③建设敢于当的政府。",
      "score": 0.8899841579523954,
      "avg_score": 0.8899841579523954,
      "bbox": [
        136.0,
        1771.0,
        516.0,
        1806.0
      ]
    },
    {
      "text": "④建设清正廉洁的政府",
      "score": 0.7691933079199358,
      "avg_score": 0.7691933079199358,
      "bbox": [
        134.0,
        1817.0,
        470.0,
        1854.0
      ]
    },
    {
      "text": "③建设阳光型政庭，做到政务公开，自觉接受人民监督。",
      "score": 0.8646772458003118,
      "avg_score": 0.8646772458003118,
      "bbox": [
        133.0,
        1860.0,
        974.0,
        1899.0
      ]
    },
    {
      "text": "（为什么要建设这样的政府？因为人民是国家的主人，行政机关的权力来自人民，是人民",
      "score": 0.9320880457758903,
      "avg_score": 0.9320880457758903,
      "bbox": [
        148.0,
        1910.0,
        1447.0,
        1949.0
      ]
    },
    {
      "text": "授予的。）",
      "score": 0.7359419067700704,
      "avg_score": 0.7359419067700704,
      "bbox": [
        133.0,
        1962.0,
        293.0,
        2002.0
      ]
    },
    {
      "text": "页5",
      "score": 0.6635201573371887,
      "avg_score": 0.6635201573371887,
      "bbox": [
        141.0,
        2045.0,
        202.0,
        2079.0
      ]
    },
    {
      "text": "57",
      "score": 0.6611524621645609,
      "avg_score": 0.6611524621645609,
      "bbox": [
        785.0,
        2070.0,
        874.0,
        2148.0
      ]
    },
    {
      "text": "扫描全能王 创建",
      "score": 0.8457870086034139,
      "avg_score": 0.8457870086034139,
      "bbox": [
        1328.0,
        2256.0,
        1597.0,
        2289.0
      ]
    }
  ]
}
