{"binding_scene":"RESEARCH","claims":{"academic_correctness":"NOT_EVALUATED","author_personality_inferred":false,"identity_verified":false,"sample_text_embedded":false},"confidence":"DEFAULT","defaults":{"disclosure_required":true,"personal_voice_claim_allowed":false,"reason":"NO_ELIGIBLE_AUTHOR_TEXT","scene":"RESEARCH","use_scene_default":true},"features":[],"negative_controls":[],"policy_binding":{"dedup_policy_sha256":"adfff05f8df904880a9a2858eda6db08c6ca8c613d9a8b94480bc29bb64174cc","feature_registry_sha256":"1070e19cc8968fb260053380a3b34c5b114e1feb41389c815151251bf7876dd9","role_policy_sha256":"e092658ff701c6e4e8d03b04b9eeb54f2a5da3bb5bb777e9d4e81caa63c988cc","scene_default_policy_sha256":"9ec0ecba7b41ee2782e5c9fa70e5929ae008afa101383c380ad1f9671df536d1"},"profile_id":"scene-default-research","profile_kind":"DEFAULT","profile_sha256":"0f121192f05109d177b82d4f2b3cecb6172e3d3d506612aaf2d6b1ddc20c0eb9","revision":1,"sample_binding":{"manifest_sha256":"01cbb04674ca386c4987966c94921c0a1c297ad29545e7264e8c223c848a882e","readable_author_chars":0,"sample_scenes":[],"unique_analysis_units":0,"unique_complete_units":0},"scene_default":{"policy_version":1,"style_codes":["RESTRAINED_FORMAL","ARGUMENT_HIERARCHY","NO_DEFENSE_OR_PROMOTION_VOICE","NO_OVER_CLOSED_ENDING"]},"schema_version":"humanize-voice-profile/v1","source_kind":"SCENE_DEFAULT","supersedes_profile_sha256":null,"validation_status":"PASS","version":1}
