{
  "notice": "扫描结果只能作为上下文复核候选。不得输出作者身份、AIGC 分数或任何概率判断。",
  "finding_count": 1,
  "candidate_count": 1,
  "findings": [
    {
      "file": "D:\\code LateX\\elegantbook\\physics\\build\\maturity-v40-cross-scene-20260719\\fixtures\\modeling.tex",
      "line": 21,
      "column": 1,
      "matched": "表格的作用也在于",
      "context": "策收益在不同约束条件下被保留了多少、损失了多少。把这层关系写清楚，才能让问题二从“珍稀物种是否增加”上升为“珍稀物种响应机制如何分化”。 表格的作用也在于让读者一眼看出每个参数到底来自哪条事实链，而不是把变量当成纯数学符号使用。这样写，问题二的证据链就会更完整：上游是禁渔和食源恢复，中间是通道",
      "count": 1,
      "action": "REVIEW",
      "signal_id": "LEX-TABLE-ROLE-01",
      "category": "table-role-ambiguity",
      "label": "表格功能句需区分读者说明与编辑后台",
      "scene": "AUTO",
      "severity": "medium",
      "candidate": true,
      "protected": false,
      "protection": null,
      "excluded": false,
      "exclusion": null,
      "rationale": "表格功能句可能是待删除的编辑计划，也可能解释现有表示为何有用；必须先确认段落职责，不能按短语整句删除。"
    }
  ],
  "coverage": {
    "status": "PASS",
    "requested_count": 1,
    "scanned_count": 1,
    "skipped_count": 0,
    "requested_files": [
      "D:\\code LateX\\elegantbook\\physics\\build\\maturity-v40-cross-scene-20260719\\fixtures\\modeling.tex"
    ],
    "scanned_files": [
      "D:\\code LateX\\elegantbook\\physics\\build\\maturity-v40-cross-scene-20260719\\fixtures\\modeling.tex"
    ],
    "skipped_files": []
  }
}
